MANIFEST.in
README.md
requirements.txt
setup.cfg
setup.py
salientregions/README.md
salientregions/__init__.py
salientregions/__init__.pyc
salientregions/binarization.py
salientregions/binarization.pyc
salientregions/binarydetector.py
salientregions/binarydetector.pyc
salientregions/detectors.py
salientregions/detectors.pyc
salientregions/helpers.py
salientregions/helpers.pyc
salientregions.egg-info/PKG-INFO
salientregions.egg-info/SOURCES.txt
salientregions.egg-info/dependency_links.txt
salientregions.egg-info/requires.txt
salientregions.egg-info/top_level.txt
tests/__init__.py
tests/__init__.pyc
tests/context.py
tests/context.pyc
tests/test_binarizers.py
tests/test_binarizers.pyc
tests/test_binary_detector.py
tests/test_binary_detector.pyc
tests/test_detectors.py
tests/test_detectors.pyc
tests/test_helpers.py
tests/test_helpers.pyc