Metadata-Version: 1.1
Name: salientregions
Version: 1.0.3
Summary: Package for finding salient regions in images
Home-page: https://github.com/NLeSC/SalientRegions-python
Author: Netherlands eScience Center
Author-email: UNKNOWN
License: UNKNOWN
Download-URL: https://github.com/NLeSC/SalientDetector-python/tarball/v1.0.3
Platform: UNKNOWN
